Metadata-Version: 2.1
Name: bob.bio.gmm
Version: 4.0.1
Summary: Tools for running biometric recognition experiments using GMM-based approximation
Home-page: https://gitlab.idiap.ch/bob/bob.bio.gmm
Author: Andre Anjos
Author-email: andre.anjos@idiap.ch
License: BSD
Keywords: bob,biometric recognition,evaluation
Platform: UNKNOWN
Classifier: Framework :: Bob
Classifier: Development Status :: 3 - Alpha
Classifier: Intended Audience :: Developers
Classifier: License :: OSI Approved :: BSD License
Classifier: Natural Language :: English
Classifier: Programming Language :: Python
Classifier: Topic :: Scientific/Engineering :: Artificial Intelligence
License-File: LICENSE
